CHANGELOG.md
LICENSE
MANIFEST.in
README.md
README.rst
requirements.txt
setup.cfg
setup.py
changelog_helper/__init__.py
changelog_helper/add_changelog.py
changelog_helper/release_changelog.py
changelog_helper/version.py
changelog_helper.egg-info/PKG-INFO
changelog_helper.egg-info/SOURCES.txt
changelog_helper.egg-info/dependency_links.txt
changelog_helper.egg-info/entry_points.txt
changelog_helper.egg-info/not-zip-safe
changelog_helper.egg-info/requires.txt
changelog_helper.egg-info/top_level.txt