Metadata-Version: 1.1
Name: changelog-helper
Version: 1.1.0
Summary: Simple scripts for creating and compiling changelog files.
Home-page: https://github.com/istarion/changelog-helper
Author: Sergey Zavgorodniy
Author-email: s.zavgorodniy@i-dgtl.ru
License: UNKNOWN
Download-URL: https://github.com/istarion/changelog-helper/archive/1.1.0.tar.gz
Keywords: git changelog generator
Platform: UNKNOWN
Classifier: Programming Language :: Python
Classifier: Programming Language :: Python :: 2
Classifier: Programming Language :: Python :: 3
Classifier: Environment :: Console
